{
  "3": {
    "ECLI:BE:CASS:2011:ARR.20110106.3": {
      "court": "CASS",
      "date": "2011-01-06",
      "roleNumber": "C.09.0231.F",
      "sitemap": [
        "https://juportal.just.fgov.be/JUPORTAsitemap/2011/01/06/sitemap_5.xml"
      ],
      "abstractFR": [
        "Pour le calcul de la cotisation patronale réellement supportée par la commune dans la charge des pensions des anciens membres du personnel du service régional d'incendie, il convient en vertu de l'article 3 de l'arrêté ministériel du 10 octobre 1977 déterminant les normes de fixation de la redevance forfaitaire et annuelle prévue à l'article 10 de la loi du 31 décembre 1963 sur la protection civile de prendre en considération le critère général de répartition de la charge patronale des pensions qui est inscrit à l'article 13 du règlement du service des pensions du 1er janvier 1935 de la commune et qui consiste en une répartition proportionnelle de ladite charge au prorata des pensions versées (1). (1) Voir les conclusions du ministère public."
      ],
      "abstractNL": [
        "Voor de berekening van de bijdrage van de werkgever die de gemeente werkelijk gedragen heeft in de pensioenlast van de gewezen personeelsleden van de gewestelijke brandweerdienst, dient krachtens artikel 3 van het ministerieel besluit van 10 oktober 1977 tot vaststelling van de normen voor het bepalen van de forfaitaire en jaarlijkse bijdrage bedoeld in artikel 10 van de wet van 31 december 1963 betreffende de civiele bescherming, als algemeen criterium te worden uitgegaan van de omslag van het aandeel van de werkgever in de pensioenen dat is vastgelegd in artikel 13 van het reglement van de pensioendienst van 1 januari 1935 van de gemeente en dat bestaat in een evenredige verdeling van die last naar rato van de gestorte pensioenen (1). (1) Zie de concl. van het O.M."
      ]
    }
  }
}