{
  "1": {
    "ECLI:BE:CASS:2008:ARR.20080124.3": {
      "court": "CASS",
      "date": "2008-01-24",
      "roleNumber": "C.07.0291.N",
      "sitemap": [
        "https://juportal.just.fgov.be/JUPORTAsitemap/2008/01/24/sitemap_4.xml"
      ],
      "abstractFR": [
        "Pour qu'un testament international soit valable en la forme devant un notaire belge, il est requis que les deux témoins ne soient pas alliés du testateur au troisième degré."
      ],
      "abstractNL": [
        "Opdat een internationaal testament voor een Belgische notaris geldig is naar de vorm, is het vereist dat de twee getuigen geen aanverwant zijn in de derde graad van de erflater."
      ]
    }
  }
}