{
  "8": {
    "ECLI:BE:CASS:1991:ARR.19910626.18": {
      "court": "CASS",
      "date": "1991-06-26",
      "roleNumber": "8920",
      "sitemap": [
        "https://juportal.just.fgov.be/JUPORTAsitemap/1991/06/26/sitemap_16.xml"
      ],
      "abstractFR": [
        "L'action publique résultant d'une infraction aux dispositions de l'arrêté royal du 13 janvier 1986 relatif au transport des marchandises dangereuses par route, à l'exception des matières explosibles et radioactives est prescrite après un an à compter du jour où l'infraction a été commise lorsqu'il s'agit d'une infraction aux prescriptions relatives à la manière de transporter les marchandises dangereuses, aux prescriptions générales de service ou aux prescriptions relatives à la circulation des véhicules. ( Loi relative à la police de la circulation routière, art. 68; A.R. du 13 janvier 1986, art. 8. )"
      ],
      "abstractNL": [
        "De strafvordering wegens overtreding van de bepalingen van het K.B. van 13 januari 1986 betreffende het vervoer van gevaarlijke goederen over de weg, met uitzondering van ontplofbare en radio-actieve stoffen verjaart door verloop van één jaar te rekenen van de dag waarop het misdrijf is begaan, wanneer het gaat om een overtreding van de voorschriften betreffende de wijze waarop de gevaarlijke goederen worden vervoerd, betreffende de algemene dienstvoorschriften en de speciale voorschriften voor onderweg. ( Art. 68, Wegverkeerswet van 16 maart 1968; art. 8, K.B. van 13 januari 1986. )"
      ]
    }
  }
}