{
  "11": {
    "ECLI:BE:CASS:2024:ARR.20241209.3F.2": {
      "court": "CASS",
      "date": "2024-12-09",
      "roleNumber": "C.23.0078.F",
      "sitemap": [
        "https://juportal.just.fgov.be/JUPORTAsitemap/2025/10/18/sitemap_2284.xml",
        "https://juportal.just.fgov.be/JUPORTAsitemap/2025/10/17/sitemap_2284.xml",
        "https://juportal.just.fgov.be/JUPORTAsitemap/2025/01/31/sitemap_99.xml"
      ],
      "abstractFR": [
        "Les dispositions des lois sur les pensions militaires relatives à la pension pour ancienneté de service ne sont pas applicables à la période de carrière d'officier auxiliaire qui a pris fin avant le 1er juin 1984 (1). (1) Voir les concl. du MP."
      ],
      "abstractNL": null
    }
  }
}