{
  "42": {
    "ECLI:BE:CASS:2019:ARR.20190905.4": {
      "court": "CASS",
      "date": "2019-09-05",
      "roleNumber": "C.18.0463.N",
      "url": "https://juportal.just.fgov.be/content/ViewDecision.php?id=ECLI:BE:CASS:2019:ARR.20190905.4&lang=fr",
      "abstractFR": [
        "Une loi nouvelle s'applique, en principe, non seulement aux situations qui naissent après son entrée en vigueur mais également aux effets futurs de la situation née sous le régime de la loi antérieure qui se produisent ou se prolongent sous l'empire de la loi nouvelle, pour autant que cette application ne porte pas atteinte à des droits déjà irrévocablement fixés; en matière de conventions, la loi ancienne demeure applicable aux effets futurs, à moins que la loi nouvelle ne soit d'ordre public ou n'en prescrive expressément l'application aux conventions en cours; les règles relatives au divorce concernent un statut légal revêtant un caractère d'ordre public, qui produit des effets en droit patrimonial (1). (1) Voir les concl. du MP publiées à leur date dans AC."
      ],
      "abstractNL": [
        "Een nieuwe wet is in beginsel niet alleen van toepassing op toestanden die na haar inwerkingtreding ontstaan, maar ook op de toekomstige gevolgen van de onder de vroegere wet ontstane toestand, die zich voordoen of voortduren onder vigeur van de nieuwe wet, voor zover die toepassing geen afbreuk doet aan reeds onherroepelijk vastgestelde rechten; inzake overeenkomsten blijft de oude wet van toepassing op de toekomstige gevolgen, tenzij de nieuwe wet van openbare orde of van dwingend recht is of uitdrukkelijk de toepassing ervan oplegt op de lopende overeenkomsten; de regels betreffende de echtscheiding betreffen een wettelijk statuut met openbare orde karakter waarvan de gevolgen vermogensrechtelijk doorwerken (1). (1) Zie concl. OM."
      ]
    }
  }
}