{
  "8": {
    "ECLI:BE:CASS:1993:ARR.19931104.5": {
      "court": "CASS",
      "date": "1993-11-04",
      "roleNumber": null,
      "sitemap": [
        "https://juportal.just.fgov.be/JUPORTAsitemap/1993/11/04/sitemap_9.xml"
      ],
      "abstractFR": [
        "Ni la Convention de sauvegarde des droits de l'homme, ni la Convention relative aux droits de l'enfant n'imposent aux tribunaux l'obligation de donner la prépondérance aux liens du sang."
      ],
      "abstractNL": [
        "Noch her verdrag tot bescherming van de rechten van de mens, noch het Verdrag betreffende de rechten van het kind leggen aan de rechtbanken op de voorkeur te geven aan de bloedband."
      ]
    }
  },
  "43": {
    "ECLI:BE:CASS:1996:ARR.19960617.10": {
      "court": "CASS",
      "date": "1996-06-17",
      "roleNumber": "S950145N",
      "sitemap": [
        "https://juportal.just.fgov.be/JUPORTAsitemap/1996/06/17/sitemap_4.xml"
      ],
      "abstractFR": [
        "Le travailleur étranger, candidat réfugié politique, qui est en possession d'un permis de travail provisoire ne remplit pas les conditions prévues par l'article 43 de l'arrêté royal du 25 novembre 1991 pour être admis au bénéfice des allocations de chômage, s'il ne respecte pas la législation relative aux étrangers et celle relative à l'emploi des travailleurs étrangers."
      ],
      "abstractNL": [
        "De vreemde arbeider, kandidaat-politiek vluchteling, in het bezit van een voorlopige toelating tot tewerkstelling voldoet niet aan de in art. 43 van het Werkloosheidsbesluit van 25 nov. 1991, om toegelaten te worden tot het recht op werkloosheidsuitkeringen, indien hij niet voldoet aan de wetgeving met betrekking op de vreemdelingen en op deze die betrekking heeft op de tewerkstelling van vreemde arbeidskrachten."
      ]
    }
  },
  "1319": {
    "ECLI:BE:CASS:2002:ARR.20021223.14": {
      "court": "CASS",
      "date": "2002-12-23",
      "roleNumber": "S020050F",
      "sitemap": [
        "https://juportal.just.fgov.be/JUPORTAsitemap/2002/12/23/sitemap_7.xml"
      ],
      "abstractFR": [
        "Viole la foi due à un acte, le juge qui donne de cet acte une interprétation inconciliable avec ses termes (1). (1) Cass., 11 décembre 1989, R.G. 8694, n° é, avec concl. M.P.; 25 septembre 2000, R.G. C.99.0201.F, n° 490."
      ],
      "abstractNL": [
        "De bewijskracht van een akte wordt door de rechter miskend wanneer hij aan die akte een uitlegging geeft die onverenigbaar is met de bewoordingen ervan (1). (1) Cass., 11 dec. 1989, AR 8694, nr é, met concl. O.M. in Bull. en Pas., I, p. 449; 25 sept. 2000, AR C.99.0201.F, nr 490."
      ]
    }
  },
  "1320": {
    "ECLI:BE:CASS:2002:ARR.20021223.14": {
      "court": "CASS",
      "date": "2002-12-23",
      "roleNumber": "S020050F",
      "sitemap": [
        "https://juportal.just.fgov.be/JUPORTAsitemap/2002/12/23/sitemap_7.xml"
      ],
      "abstractFR": [
        "Viole la foi due à un acte, le juge qui donne de cet acte une interprétation inconciliable avec ses termes (1). (1) Cass., 11 décembre 1989, R.G. 8694, n° é, avec concl. M.P.; 25 septembre 2000, R.G. C.99.0201.F, n° 490."
      ],
      "abstractNL": [
        "De bewijskracht van een akte wordt door de rechter miskend wanneer hij aan die akte een uitlegging geeft die onverenigbaar is met de bewoordingen ervan (1). (1) Cass., 11 dec. 1989, AR 8694, nr é, met concl. O.M. in Bull. en Pas., I, p. 449; 25 sept. 2000, AR C.99.0201.F, nr 490."
      ]
    }
  },
  "2044": {
    "ECLI:BE:CASS:2005:ARR.20051031.4": {
      "court": "CASS",
      "date": "2005-10-31",
      "roleNumber": "S050007F",
      "sitemap": [
        "https://juportal.just.fgov.be/JUPORTAsitemap/2005/10/31/sitemap_3.xml"
      ],
      "abstractFR": [
        "La transaction est un contrat synallagmatique par lequel les parties se font mutuellement des concessions en vue de terminer ou de prévenir un litige sans pour autant que l'une des parties reconnaisse le bien-fondé des prétentions de l'autre (1). (1) Voir Cass., 15 octobre 1979 (Bull. et Pas. 1980, I, 210); 31 mars 1993, RG 300, n° 170; 19 septembre 2001, RG P.01.0617.F, n° 473."
      ],
      "abstractNL": [
        "Dading is een wederkerige overeenkomst tussen partijen die elkaar wederzijdse toegevingen doen om een geschil te beëindigen of te voorkomen, zonder dat een van de partijen de gegrondheid van de aanspraken van de andere partij daarom erkent (1). (1) Zie Cass., 15 okt. 1979, A.C., 1979-80, 197; 31 maart 1993, AR 300, nr 170; 19 sept. 2001, AR P.01.0617.F, nr 473."
      ]
    }
  },
  "general": {
    "ECLI:BE:CASS:1999:ARR.19991110.20": {
      "court": "CASS",
      "date": "1999-11-10",
      "roleNumber": "P990689F",
      "sitemap": [
        "https://juportal.just.fgov.be/JUPORTAsitemap/1999/11/10/sitemap_7.xml"
      ],
      "abstractFR": [
        "Les articles 3 et 12 de la Convention relative aux droits de l'enfant ne sont pas d'application directe pour le juge pénal saisi de poursuites du chef d'infraction à l'article 369bis du Code pénal."
      ],
      "abstractNL": [
        "Art. 3 en 12, Verdrag inzake de rechten van het kind, zijn niet rechtstreeks van toepassing voor de strafrechter waarbij de wegens schending van art. 369bis Sw. ingestelde vervolgingen aanhangig zijn."
      ]
    },
    "ECLI:BE:CASS:1999:ARR.19991104.5": {
      "court": "CASS",
      "date": "1999-11-04",
      "roleNumber": "C990048N",
      "sitemap": [
        "https://juportal.just.fgov.be/JUPORTAsitemap/1999/11/04/sitemap_4.xml"
      ],
      "abstractFR": [
        "Bien qu'elles soient utiles à l'interprétation des textes, les dispositions des articles 3, § 1er et 3, § 2 de la Convention relative aux droits de l'enfant adoptée à New York le 20 novembre 1989 ne sont pas, en soi, suffisamment précises et complètes que pour avoir un effet direct, dès lors qu'elles laissent à l'Etat plusieurs possibilités de satisfaire aux exigences de l'intérêt de l'enfant; elles ne peuvent servir de source de droits subjectifs et d'obligations dans le chef des particuliers ; elles permettent notamment aux Etats et aux autorités contractantes de déterminer comment protéger au mieux les intérêts de l'enfant dans le cadre des modalités d'établissement de la filiation biologique."
      ],
      "abstractNL": [
        "De bepalingen van de artikelen 3.1 en 3.2 van het Verdrag van 20 november 1989 inzake de rechten van het kind, ook al kunnen zij nuttig zijn bij de interpretatie van teksten, zijn op zichzelf niet voldoende nauwkeurig en volledig om directe werking te hebben, omdat zij verscheidene mogelijkheden aan de Staat laren om aan de vereisten van het belang van het kind te voldoen; zij kunnen niet gelden als bron van subjectieve rechten en van verplichtingen voor particulieren, zij laten inzonderheid de mogelijkheid open voor de verbonden Dtaten en overheden te bepalen hoe de belangen van het kind het best worden beschermd in verband met de wijze waarop de biologische afstamming wordt vastgesteld."
      ]
    },
    "ECLI:BE:CASS:1999:ARR.19991104.6": {
      "court": "CASS",
      "date": "1999-11-04",
      "roleNumber": "C990111N",
      "sitemap": [
        "https://juportal.just.fgov.be/JUPORTAsitemap/1999/11/04/sitemap_2.xml"
      ],
      "abstractFR": [
        "Bien qu'elles soient utiles à l'interprétation des textes, les dispositions des articles 3, § 1er et 3, § 2 de la Convention relative aux droits de l'enfant adoptée à New York le 20 novembre 1989 ne sont pas, en soi, suffisamment précises et complètes que pour avoir un effet direct; elles laissent à l'Etat plusieurs possibilités de satisfaire aux exigences de l'intérêt de l'enfant, mais ne peuvent servir de source de droit subjectifs et d'obligation dans le chef des particuliers; elles permettent notamment aux Etats et aux autorités contractantes de déterminer comment protéger au mieux les intérêts de l'enfant dans le cadre des modalités d'établissement de la filiation biologique. Les articles 330, § 2, et 332 du Code civil prévoient une réglementation qui protège les intérêts de l'enfant."
      ],
      "abstractNL": [
        "De bepalingen van de artikelen 3.1 en 3.2 van het Verdrag van 20 november 1989 inzake de rechten van het kind, ook al kunnen zij nuttig zijn bij de interpretatie van teksten, zijn op zichzelf niet voldoende nauwkeurig en volledig om directe werking te hebben; zij laten verscheidene mogelijkheden aan de Staat om aan de vereisten van het belang van het kind te voldoen, maar zij kunnen niet gelden als bron van subjectieve rechten en van verplichtingen voor particulieren; zij laten inzonderheid de mogelijkheid open voor de verbonden Staten en overheden te bepalenhoe de belangen van het kind het best worden beschermd in verband met de wijze waarop de biologische afstamming wordt vastgesteld. De artikelen 330, 2, en 332 van het Burgerlijk Wetboek voorzien in een regeling waarbij de belangen van het kind worden beschermd."
      ]
    },
    "ECLI:BE:CASS:1999:ARR.19990331.5": {
      "court": "CASS",
      "date": "1999-03-31",
      "roleNumber": "P990276F",
      "sitemap": [
        "https://juportal.just.fgov.be/JUPORTAsitemap/1999/03/31/sitemap_2.xml"
      ],
      "abstractFR": [
        "La mesure d'hébergement temporaire hors du milieu familial peut être justifiée notamment par le souci de permettre le rétablissement des relations personnelles normales d'un enfant avec chacun de ses père et mère."
      ],
      "abstractNL": [
        "De maatregel van tijdelijke huisvesting buiten het familiaal leefmilieu kan onder meer zijn ingegeven door de zorg om het kind in staat te stellen opnieuw normale persoonlijke relaties met ieder van zijn ouders aan te knopen."
      ]
    },
    "ECLI:BE:CASS:1994:ARR.19940311.12": {
      "court": "CASS",
      "date": "1994-03-11",
      "roleNumber": "C930342N",
      "sitemap": [
        "https://juportal.just.fgov.be/JUPORTAsitemap/1994/03/11/sitemap_2.xml"
      ],
      "abstractFR": [
        "L'autorité des parents et les droits qui en découlent devant, en vertu de la convention relative aux droits de l'enfant, toujours être exercés dans l'intérêt des enfants, le juge peut décider, dans ledit intérêt, que pendant l'exercice du droit de visite, aucune mesure d'exécution ou de coercition ne sera utilisée à l'égard des enfants. (Loi du 25 novembre 1991 portant approbation de la Convention relative aux droits de l'enfant)."
      ],
      "abstractNL": [
        "Nu, krachtens het Verdrag inzake de rechten van het kind, het ouderlijk gezag van de rechten die eruit voortvloeien steeds in het belang van de kinderen moeten worden uitgeoefend, mag de rechter in dat belang beslissen dat de ouder, bij de uitoefening van zijn omgangsrecht, geen uitvoeringsmaatregelen noch dwangmaatregelen tegen de kinderen mag gebruiken. (Wet van 25 nov. 1991, houdende goedkeuring van het Verdrag inzake de rechten van het kind)."
      ]
    },
    "ECLI:BE:CASS:1993:ARR.19931104.12": {
      "court": "CASS",
      "date": "1993-11-04",
      "roleNumber": "9613",
      "sitemap": [
        "https://juportal.just.fgov.be/JUPORTAsitemap/1993/11/04/sitemap_7.xml"
      ],
      "abstractFR": null,
      "abstractNL": [
        "Noch art. 8 EVRM , noch de bepalingen van het Verdrag inzake de Rechten van het Kind verplichten de rechtbanken ertoe bij de homologatie van een adoptie de bloedbanden als hoofdzaak te beschouwen; het belang van het kind is daarbij de voornaamste overweging. (Art. 8, EVRM ; art. 21, Verdrag inzake de Rechten van het Kind, aangenomen te New York op 20 nov. 1989, goedgekeurd bij decr. Fr. Gem. 3 juli 1991)."
      ]
    }
  }
}