{
  "1": {
    "ECLI:BE:CASS:2023:ARR.20230313.3F.4": {
      "court": "CASS",
      "date": "2023-03-13",
      "roleNumber": "C.22.0366.F",
      "url": "https://juportal.just.fgov.be/content/ViewDecision.php?id=ECLI:BE:CASS:2023:ARR.20230313.3F.4",
      "abstractFR": [
        "Les 2 novembre, 15 novembre et 26 décembre ne sont pas des jours fériés pour l'application de la loi du 17 mai 2006 (1). (1) Voir les concl. du MP."
      ],
      "abstractNL": [
        "2 november, 15 november en 26 december zijn geen feestdagen voor de toepassing van de Wet Strafuitvoering (1). (1) Zie concl. OM.",
        "2 november, 15 november en 26 december zijn geen feestdagen voor de toepassing van de Wet Strafuitvoering (1). (1) Zie concl. OM in Pas., nr. 194."
      ]
    }
  }
}