{
  "8": {
    "ECLI:BE:CASS:2012:ARR.20121123.3": {
      "court": "CASS",
      "date": "2012-11-23",
      "roleNumber": "F.11.0050.N",
      "sitemap": [
        "https://juportal.just.fgov.be/JUPORTAsitemap/2012/11/23/sitemap_12.xml"
      ],
      "abstractFR": [
        "Une réclamation contre une redevance relative aux bâtiments désaffectés ou laissés à l'abandon qui est introduite en dehors du délai de trente jours calendaires de l'envoi de l'imposition prévu par l'article 39, § 2, du Décret du Conseil flamand du 22 décembre 1995, doit néanmoins être considérée comme étant envoyée en temps utile eu égard au caractère anticonstitutionnel de cette disposition et au défaut de toute initiative législative pour y remédier (1). (1) Voir les conclusions du M.P. publiées à leur date dans AC."
      ],
      "abstractNL": [
        "Een bezwaarschrift tegen een leegstandsheffing, dat ingediend werd buiten de in artikel 39, § 2, van het Decr. Vl. R. van 22 december 1995, gestelde termijn van dertig kalenderdagen vanaf de verzending van de aanslag, dient niettemin als tijdig te worden beschouwd gelet op de ongrondwettelijkheid van deze bepaling en het gebrek aan enig wetgevend initiatief om hieraan te verhelpen (1). (1) Zie de conclusie van het O.M."
      ]
    }
  }
}