{
  "general": {
    "ECLI:BE:CASS:1970:ARR.19700601.1": {
      "court": "CASS",
      "date": "1970-06-01",
      "roleNumber": null,
      "sitemap": [
        "https://juportal.just.fgov.be/JUPORTAsitemap/1970/06/01/sitemap_1.xml"
      ],
      "abstractFR": [
        "Les dispositions transitoires prévues par les articles 30, alinéa 1er, de la loi du 3 juin 1964 et 9, b, de la loi du 22 janvier 1969 relatives au statut des objecteurs de conscience ne sont pas applicables au milicien qui a obtenu l'exemption du service militaire armé et qui sollicite l'exemption de tout service militaire."
      ],
      "abstractNL": [
        "De overgangsbepalingen vastgesteld bij de artikelen 30, lid 1, van de wet van 3 juni 1964 en 9, b, van de wet van 22 januari 1969 betreffende het statuut van de gewetensbezwaarden zijn niet van toepassing op de dienstplichtige die vrijstelling van gewapende militaire dienst heeft bekomen en vrijstelling van alle militaire dienst vraagt."
      ]
    }
  }
}